streamlit_cropper_ext/__init__.py
streamlit_cropper_ext/frontend/build/asset-manifest.json
streamlit_cropper_ext/frontend/build/bootstrap.min.css
streamlit_cropper_ext/frontend/build/index.html
streamlit_cropper_ext/frontend/build/precache-manifest.ae0e02c7a3e469991b1680ed8779762d.js
streamlit_cropper_ext/frontend/build/service-worker.js
streamlit_cropper_ext/frontend/build/static/js/2.1ef8f1af.chunk.js
streamlit_cropper_ext/frontend/build/static/js/2.1ef8f1af.chunk.js.LICENSE.txt
streamlit_cropper_ext/frontend/build/static/js/2.1ef8f1af.chunk.js.map
streamlit_cropper_ext/frontend/build/static/js/main.9a5ff069.chunk.js
streamlit_cropper_ext/frontend/build/static/js/main.9a5ff069.chunk.js.LICENSE.txt
streamlit_cropper_ext/frontend/build/static/js/main.9a5ff069.chunk.js.map
streamlit_cropper_ext/frontend/build/static/js/runtime-main.44d30fc2.js
streamlit_cropper_ext/frontend/build/static/js/runtime-main.44d30fc2.js.map
streamlit_cropper_ext-0.2.1.dist-info/LICENSE
streamlit_cropper_ext-0.2.1.dist-info/METADATA
streamlit_cropper_ext-0.2.1.dist-info/WHEEL
streamlit_cropper_ext-0.2.1.dist-info/top_level.txt
streamlit_cropper_ext-0.2.1.dist-info/RECORD
