Metadata-Version: 2.1
Name: streamlit-cropper-ext
Version: 0.2.1
Summary: A simple image cropper for Streamlit
Home-page: https://github.com/hits-sdo/streamlit-cropper
Author: SEARCH project
Author-email: Turner Anderson <andersontur11@gmail.com>
Project-URL: Homepage, https://github.com/turner-anderson/streamlit-cropper-ext
Project-URL: Bug Tracker, https://github.com/turner-anderson/streamlit-cropper-ext/issues
Classifier: Programming Language :: Python :: 3
Classifier: License :: OSI Approved :: MIT License
Classifier: Operating System :: OS Independent
Requires-Python: >=3.6
License-File: LICENSE
Requires-Dist: streamlit >=1.3.1
Requires-Dist: Pillow >=8.4.0
Requires-Dist: numpy >=1.21.5
